mercuto_client/__init__.py
mercuto_client/_authentication.py
mercuto_client/acl.py
mercuto_client/client.py
mercuto_client/exceptions.py
mercuto_client/py.typed
mercuto_client/util.py
mercuto_client/_tests/__init__.py
mercuto_client/_tests/conftest.py
mercuto_client/_tests/test_util.py
mercuto_client/_tests/test_ingester/__init__.py
mercuto_client/_tests/test_ingester/test_backup.py
mercuto_client/_tests/test_ingester/test_file_processor.py
mercuto_client/_tests/test_ingester/test_ftp.py
mercuto_client/_tests/test_ingester/test_parsers.py
mercuto_client/_tests/test_mocking/__init__.py
mercuto_client/_tests/test_mocking/conftest.py
mercuto_client/_tests/test_mocking/test_mock_identity.py
mercuto_client/ingester/__init__.py
mercuto_client/ingester/__main__.py
mercuto_client/ingester/backup.py
mercuto_client/ingester/ftp.py
mercuto_client/ingester/mercuto.py
mercuto_client/ingester/pid_file.py
mercuto_client/ingester/processor.py
mercuto_client/ingester/parsers/__init__.py
mercuto_client/ingester/parsers/campbell.py
mercuto_client/ingester/parsers/generic_csv.py
mercuto_client/ingester/parsers/worldsensing.py
mercuto_client/mocks/__init__.py
mercuto_client/mocks/_utility.py
mercuto_client/mocks/mock_core.py
mercuto_client/mocks/mock_data.py
mercuto_client/mocks/mock_fatigue.py
mercuto_client/mocks/mock_identity.py
mercuto_client/mocks/mock_media.py
mercuto_client/mocks/mock_notifications.py
mercuto_client/modules/__init__.py
mercuto_client/modules/_util.py
mercuto_client/modules/core.py
mercuto_client/modules/data.py
mercuto_client/modules/fatigue.py
mercuto_client/modules/identity.py
mercuto_client/modules/media.py
mercuto_client/modules/notifications.py
mercuto_client/modules/reports.py
mercuto_client-0.3.7.dist-info/licenses/LICENSE
mercuto_client-0.3.7.dist-info/METADATA
mercuto_client-0.3.7.dist-info/WHEEL
mercuto_client-0.3.7.dist-info/entry_points.txt
mercuto_client-0.3.7.dist-info/top_level.txt
mercuto_client-0.3.7.dist-info/RECORD
