Metadata-Version: 2.4
Name: mercuto-client
Version: 0.3.7
Summary: Library for interfacing with Rockfield's Mercuto API
Author-email: Daniel Whipp <daniel.whipp@rocktech.com.au>
License-Expression: AGPL-3.0-only
Project-URL: Homepage, https://mercuto.rockfieldcloud.com.au
Project-URL: Repository, https://github.com/RockfieldTechnologiesAustralia/mercuto-client
Project-URL: Documentation, https://github.com/RockfieldTechnologiesAustralia/mercuto-client/blob/main/README.md
Keywords: mercuto,rockfield,infratech
Classifier: Development Status :: 3 - Alpha
Classifier: Intended Audience :: Developers
Classifier: Topic :: Software Development :: Build Tools
Classifier: Programming Language :: Python :: 3.10
Classifier: Programming Language :: Python :: 3.11
Classifier: Programming Language :: Python :: 3.12
Requires-Python: >=3.10
License-File: LICENSE
Requires-Dist: requests>=2.32
Requires-Dist: pyftpdlib>=2.0.1
Requires-Dist: python-dateutil>=2.9.0.post0
Requires-Dist: pytz>=2025.2
Requires-Dist: schedule>=1.2.2
Requires-Dist: zc.lockfile>=4.0
Requires-Dist: pydantic>=2.0
Dynamic: license-file
